netbox_meraki/__init__.py
netbox_meraki/admin.py
netbox_meraki/forms.py
netbox_meraki/jobs.py
netbox_meraki/meraki_client.py
netbox_meraki/models.py
netbox_meraki/navigation.py
netbox_meraki/sync_service.py
netbox_meraki/urls.py
netbox_meraki/views.py
netbox_meraki/api/__init__.py
netbox_meraki/api/serializers.py
netbox_meraki/api/urls.py
netbox_meraki/api/views.py
netbox_meraki/management/__init__.py
netbox_meraki/management/commands/__init__.py
netbox_meraki/management/commands/sync_meraki.py
netbox_meraki/migrations/0001_initial.py
netbox_meraki/migrations/__init__.py
netbox_meraki/templates/netbox_meraki/base.html
netbox_meraki/templates/netbox_meraki/config.html
netbox_meraki/templates/netbox_meraki/dashboard.html
netbox_meraki/templates/netbox_meraki/job_history.html
netbox_meraki/templates/netbox_meraki/prefixfilterrule_confirm_delete.html
netbox_meraki/templates/netbox_meraki/prefixfilterrule_form.html
netbox_meraki/templates/netbox_meraki/prefixfilterrule_list.html
netbox_meraki/templates/netbox_meraki/review_detail.html
netbox_meraki/templates/netbox_meraki/review_detail_new.html
netbox_meraki/templates/netbox_meraki/review_item_edit.html
netbox_meraki/templates/netbox_meraki/review_list.html
netbox_meraki/templates/netbox_meraki/scheduled_sync.html
netbox_meraki/templates/netbox_meraki/scheduled_sync_edit.html
netbox_meraki/templates/netbox_meraki/sitenamerule_confirm_delete.html
netbox_meraki/templates/netbox_meraki/sitenamerule_form.html
netbox_meraki/templates/netbox_meraki/sitenamerule_list.html
netbox_meraki/templates/netbox_meraki/sync.html
netbox_meraki/templates/netbox_meraki/synclog.html
netbox_meraki/templatetags/__init__.py
netbox_meraki/templatetags/meraki_extras.py
netbox_meraki-1.1.0.dist-info/licenses/LICENSE
netbox_meraki-1.1.0.dist-info/METADATA
netbox_meraki-1.1.0.dist-info/WHEEL
netbox_meraki-1.1.0.dist-info/top_level.txt
netbox_meraki-1.1.0.dist-info/RECORD
