Metadata-Version: 2.4
Name: netbox-meraki
Version: 1.1.0
Summary: NetBox plugin for synchronizing Cisco Meraki Dashboard networks, devices, VLANs, and prefixes
Author: Tarani Debnath
Project-URL: Homepage, https://github.com/tkdebnath/netbox-meraki
Project-URL: Repository, https://github.com/tkdebnath/netbox-meraki
Project-URL: Issues, https://github.com/tkdebnath/netbox-meraki/issues
Project-URL: Changelog, https://github.com/tkdebnath/netbox-meraki/blob/main/CHANGELOG.md
Keywords: netbox,meraki,cisco,plugin,network,automation,ipam,dcim
Classifier: Development Status :: 5 - Production/Stable
Classifier: Framework :: Django
Classifier: Intended Audience :: System Administrators
Classifier: Intended Audience :: Telecommunications Industry
Classifier: License :: OSI Approved :: Apache Software License
Classifier: Programming Language :: Python :: 3
Classifier: Programming Language :: Python :: 3.10
Classifier: Programming Language :: Python :: 3.11
Classifier: Programming Language :: Python :: 3.12
Classifier: Topic :: System :: Networking
Classifier: Topic :: System :: Systems Administration
Requires-Python: >=3.10
License-File: LICENSE
Requires-Dist: requests>=2.31.0
Dynamic: license-file
